LICENSE
MANIFEST.in
README.md
pyproject.toml
test/__init__.py
test/conftest.py
test/test_connection.py
test/test_crazy_window_script.py
test/test_fakeinput.py
test/test_python_code.py
test/test_render.py
test/test_xkb.py
xcffib/__init__.py
xcffib/bigreq.py
xcffib/composite.py
xcffib/damage.py
xcffib/dbe.py
xcffib/dpms.py
xcffib/dri2.py
xcffib/dri3.py
xcffib/ffi.py
xcffib/ge.py
xcffib/glx.py
xcffib/present.py
xcffib/py.typed
xcffib/randr.py
xcffib/record.py
xcffib/render.py
xcffib/res.py
xcffib/screensaver.py
xcffib/shape.py
xcffib/shm.py
xcffib/sync.py
xcffib/testing.py
xcffib/wrappers.py
xcffib/xc_misc.py
xcffib/xevie.py
xcffib/xf86dri.py
xcffib/xf86vidmode.py
xcffib/xfixes.py
xcffib/xinerama.py
xcffib/xinput.py
xcffib/xkb.py
xcffib/xprint.py
xcffib/xproto.py
xcffib/xselinux.py
xcffib/xtest.py
xcffib/xv.py
xcffib/xvmc.py
xcffib.egg-info/PKG-INFO
xcffib.egg-info/SOURCES.txt
xcffib.egg-info/dependency_links.txt
xcffib.egg-info/requires.txt
xcffib.egg-info/top_level.txt