Metadata-Version: 2.4
Name: xcffib
Version: 1.10.0
Summary: xcffib is the XCB binding for python
Author-email: Tycho Andersen <tycho@tycho.pizza>
License: Apache License 2.0
Project-URL: Homepage, http://github.com/tych0/xcffib
Keywords: xcb,cffi,x11,x,windows
Classifier: Development Status :: 5 - Production/Stable
Classifier: License :: OSI Approved :: Apache Software License
Classifier: Programming Language :: Python :: 3
Classifier: Programming Language :: Python :: Implementation :: CPython
Classifier: Programming Language :: Python :: Implementation :: PyPy
Classifier: Topic :: Software Development :: Libraries
Requires-Python: >=3.10
License-File: LICENSE
Requires-Dist: cffi>=1.1.0; platform_python_implementation != "PyPy"
Provides-Extra: dev
Requires-Dist: pytest>=8.4; extra == "dev"
Dynamic: license-file
